gypt_matplotlib/__init__.py
gypt_matplotlib/constants.py
gypt_matplotlib/context_managers.py
gypt_matplotlib/errors.py
gypt_matplotlib/gypt.mplstyle
gypt_matplotlib/utils.py
gypt_matplotlib-0.4.5.dist-info/METADATA
gypt_matplotlib-0.4.5.dist-info/WHEEL
gypt_matplotlib-0.4.5.dist-info/licenses/LICENSE
gypt_matplotlib-0.4.5.dist-info/RECORD
