Metadata-Version: 2.4
Name: gypt_matplotlib
Version: 0.4.5
Summary: A small addon for matplotlib that can be used for the GYPT.
License-Expression: MIT
License-File: LICENSE
Keywords: Albert Unruh,GYPT,German Young Physicists' Tournament,matplotlib,addon
Author: Keenan Noack
Author-email: gypt-matplotlib@albertunruh.de
Requires-Python: >=3.12
Classifier: Framework :: Matplotlib
Classifier: Intended Audience :: Education
Classifier: Intended Audience :: Science/Research
Classifier: License :: OSI Approved :: MIT License
Classifier: Natural Language :: German
Classifier: Natural Language :: English
Classifier: Operating System :: OS Independent
Classifier: Programming Language :: Python :: 3
Classifier: Programming Language :: Python :: 3 :: Only
Classifier: Programming Language :: Python :: 3.12
Classifier: Programming Language :: Python :: 3.13
Classifier: Programming Language :: Python :: 3.14
Classifier: Topic :: Scientific/Engineering :: Physics
Classifier: Topic :: Scientific/Engineering :: Visualization
Classifier: Topic :: Utilities
Classifier: Typing :: Typed
Requires-Dist: matplotlib (>=3.10.8,<4.0.0)
Requires-Dist: pillow (>=12.1.0,<13.0.0)
Requires-Dist: pyqt6 (>=6.10.2,<7.0.0)
Requires-Dist: ruff (>=0.14.14,<0.15.0)
Project-URL: Homepage, https://codeberg.org/AlbertUnruh/gypt-matplotlib
Project-URL: issues, https://codeberg.org/AlbertUnruh/gypt-matplotlib/issues
Project-URL: soucecode, https://codeberg.org/AlbertUnruh/gypt-matplotlib
